fuzzy_hash/__init__.py
fuzzy_hash/lib/__init__.py
fuzzy_hash/lib/core.cpython-38-darwin.so
fuzzy_hash/lib/setup.py
fuzzy_hash-0.0.3.dist-info/METADATA
fuzzy_hash-0.0.3.dist-info/WHEEL
fuzzy_hash-0.0.3.dist-info/top_level.txt
fuzzy_hash-0.0.3.dist-info/RECORD
