Metadata-Version: 2.1
Name: fuzzy-hash
Version: 0.0.3
Summary: Fuzzy Hash in python
Requires-Python: >=3.5
